hopp/__init__.py
hopp/logging_manager.py
hopp/type_dec.py
hopp/simulation/__init__.py
hopp/simulation/base.py
hopp/simulation/hopp.py
hopp/simulation/hopp_interface.py
hopp/simulation/hybrid_simulation.py
hopp/simulation/resource_files/site_details.csv
hopp/simulation/resource_files/utility_rate_response.json
hopp/simulation/resource_files/cambium/Cambium23_MidCase100by2035_hourly_West_Connect_North_2025.csv
hopp/simulation/resource_files/cambium/Cambium23_MidCase100by2035_hourly_West_Connect_North_2030.csv
hopp/simulation/resource_files/cambium/Cambium23_MidCase100by2035_hourly_West_Connect_North_2035.csv
hopp/simulation/resource_files/cambium/Cambium23_MidCase100by2035_hourly_West_Connect_North_2040.csv
hopp/simulation/resource_files/cambium/Cambium23_MidCase100by2035_hourly_West_Connect_North_2045.csv
hopp/simulation/resource_files/cambium/Cambium23_MidCase100by2035_hourly_West_Connect_North_2050.csv
hopp/simulation/resource_files/greet/README.md
hopp/simulation/resource_files/greet/2023/greet_2023_processed.yaml
hopp/simulation/resource_files/greet/2023/ccs_central_h2_prod/GREET1_2023_Rev1.xlsm
hopp/simulation/resource_files/greet/2023/ccs_central_h2_prod/GREET2_2023_Rev1.xlsm
hopp/simulation/resource_files/greet/2023/no_ccs_central_h2_prod/GREET1_2023_Rev1.xlsm
hopp/simulation/resource_files/greet/2023/no_ccs_central_h2_prod/GREET2_2023_Rev1.xlsm
hopp/simulation/resource_files/grid/dispatch_factors_ts.csv
hopp/simulation/resource_files/grid/pricing-data-2015-IronMtn-002_factors.csv
hopp/simulation/resource_files/solar/34.865371_-116.783023_psmv3_60_tmy.csv
hopp/simulation/resource_files/solar/35.2018863_-101.945027_psmv3_60_2012.csv
hopp/simulation/resource_files/solar/39.7555_-105.2211_psmv3_60_2012.csv
hopp/simulation/resource_files/tidal/Tidal_resource_timeseries.csv
hopp/simulation/resource_files/wave/Wave_resource_timeseries.csv
hopp/simulation/resource_files/wind/35.2018863_-101.945027_BC_HRRR_2015_60min_80m_100m.csv
hopp-3.4.1.dist-info/licenses/LICENSE
hopp-3.4.1.dist-info/METADATA
hopp-3.4.1.dist-info/WHEEL
hopp-3.4.1.dist-info/top_level.txt
hopp-3.4.1.dist-info/RECORD
