Metadata-Version: 2.4
Name: hopp
Version: 3.4.1
Summary: Hybrid Systems Optimization and Performance Platform.
Author-email: NREL <dguittet@nrel.gov>
License: BSD 3-Clause License
Project-URL: source, https://github.com/NREL/HOPP
Project-URL: documentation, https://hopp.readthedocs.io/
Project-URL: issues, https://github.com/NREL/HOPP/issues
Project-URL: changelog, https://github.com/NREL/HOPP/blob/main/RELEASE.md
Keywords: python3,hybrid-energy,wind-energy,solar-energy,layout-optimization
Classifier: Development Status :: 5 - Production/Stable
Classifier: Intended Audience :: Developers
Classifier: Intended Audience :: Science/Research
Classifier: Intended Audience :: Other Audience
Classifier: License :: OSI Approved :: BSD License
Classifier: Natural Language :: English
Classifier: Operating System :: OS Independent
Classifier: Programming Language :: Python
Classifier: Programming Language :: Python :: 3 :: Only
Classifier: Programming Language :: Python :: 3.11
Classifier: Programming Language :: Python :: 3.12
Classifier: Programming Language :: Python :: 3.13
Classifier: Topic :: Scientific/Engineering
Classifier: Topic :: Software Development :: Libraries :: Python Modules
Requires-Python: >=3.11
License-File: LICENSE
Requires-Dist: Cython
Requires-Dist: NREL-PySAM>=7.0.0
Requires-Dist: Pillow
Requires-Dist: Pyomo>=6.1.2
Requires-Dist: fastkml<1
Requires-Dist: floris==4.3
Requires-Dist: future
Requires-Dist: global_land_mask
Requires-Dist: lcoe
Requires-Dist: lxml
Requires-Dist: matplotlib
Requires-Dist: multiprocessing-on-dill
Requires-Dist: numpy
Requires-Dist: numpy-financial
Requires-Dist: pandas>=2.0.3
Requires-Dist: pint
Requires-Dist: pvmismatch
Requires-Dist: pyDOE2
Requires-Dist: pyproj
Requires-Dist: pysolar
Requires-Dist: python-dotenv
Requires-Dist: python-rapidjson
Requires-Dist: pytz
Requires-Dist: rainflow
Requires-Dist: requests
Requires-Dist: scikit-learn
Requires-Dist: scikit-optimize
Requires-Dist: scipy
Requires-Dist: shapely>=2
Requires-Dist: setuptools
Requires-Dist: timezonefinder==6.5.9
Requires-Dist: openpyxl
Requires-Dist: attrs
Requires-Dist: utm
Requires-Dist: pyyaml-include
Requires-Dist: profast
Requires-Dist: NREL-rex
Requires-Dist: turbine-models>=0.1.0
Provides-Extra: develop
Requires-Dist: pytest; extra == "develop"
Requires-Dist: pytest-subtests; extra == "develop"
Requires-Dist: pytest-dependency; extra == "develop"
Requires-Dist: responses; extra == "develop"
Requires-Dist: jupyter-book<2; extra == "develop"
Requires-Dist: sphinxcontrib-napoleon; extra == "develop"
Provides-Extra: examples
Requires-Dist: jupyterlab; extra == "examples"
Provides-Extra: all
Requires-Dist: hopp[develop,examples]; extra == "all"
Dynamic: license-file
